save_url/__init__.py
save_url/core.py
save_url/locale/en/LC_MESSAGES/save_url.mo
save_url/locale/en.po
save_url/locale/es/LC_MESSAGES/save_url.mo
save_url/locale/es.po
save_url/locale/save_url.pot
save_url/poethepoet.py
save_url-1.0.0.dist-info/LICENSE.txt
save_url-1.0.0.dist-info/METADATA
save_url-1.0.0.dist-info/WHEEL
save_url-1.0.0.dist-info/entry_points.txt
save_url-1.0.0.dist-info/RECORD
