Metadata-Version: 2.3
Name: save_url
Version: 1.0.0
Summary: Script to save and url in a single file with an automatic and structured name. It uses monolith as its backend
License: GPL-3.0-only
Author: turulomio
Author-email: turulomio@yahoo.es
Requires-Python: >=3.11,<4.0.0
Classifier: License :: OSI Approved :: GNU General Public License v3 (GPLv3)
Classifier: Programming Language :: Python :: 3
Classifier: Programming Language :: Python :: 3.11
Classifier: Programming Language :: Python :: 3.12
Classifier: Programming Language :: Python :: 3.13
Requires-Dist: colorama (>=0.4.6,<0.5.0)
Requires-Dist: mechanize (>=0.4.8)
Project-URL: Homepage, https://github.com/turulomio/save_url/
Project-URL: Repository, https://github.com/turulomio/save_url/
Project-URL: changelog, https://github.com/turulomio/save_url#changelog
